co2sys/CO2SYS.m
co2sys/__init__.py
co2sys/calculations.py
co2sys/co2sys.py
co2sys/constants.py
co2sys/octave-workspace
co2sys-0.1.1.dist-info/WHEEL
co2sys-0.1.1.dist-info/METADATA
co2sys-0.1.1.dist-info/RECORD
