Metadata-Version: 2.1
Name: co2sys
Version: 0.1.1
Summary: 
Author: Bror Jonsson
Author-email: brorfred@gmail.com
Requires-Python: >=3.6,<4.0
Classifier: Programming Language :: Python :: 3
Classifier: Programming Language :: Python :: 3.6
Classifier: Programming Language :: Python :: 3.7
Requires-Dist: numpy (>=1.17,<2.0)
